[
  {
    "question": "Yoruba people are mainly from",
    "options": [
      "Southern Nigeria",
      "Western Nigeria",
      "Northern Nigeria",
      "Eastern Nigeria"
    ],
    "answer": "Western Nigeria"
  },
  {
    "question": "'Bawo' in Yoruba means",
    "options": [
      "Goodbye",
      "Hello/How are you",
      "Thank you",
      "Please"
    ],
    "answer": "Hello/How are you"
  },
  {
    "question": "The Yoruba kingdom was called",
    "options": [
      "Mali",
      "Oyo",
      "Benin",
      "Kano"
    ],
    "answer": "Oyo"
  },
  {
    "question": "Yoruba language has",
    "options": [
      "3 tones",
      "2 tones",
      "4 tones",
      "5 tones"
    ],
    "answer": "3 tones"
  },
  {
    "question": "Yoruba cultural heritage includes",
    "options": [
      "only music",
      "art, music, and dance",
      "only dance",
      "only art"
    ],
    "answer": "art, music, and dance"
  },
  {
    "question": "'E pele' in Yoruba means",
    "options": [
      "Thank you",
      "Sorry/Take it easy",
      "Hello",
      "Goodbye"
    ],
    "answer": "Sorry/Take it easy"
  },
  {
    "question": "Yoruba people are known for",
    "options": [
      "hunting",
      "weaving and crafts",
      "mining",
      "manufacturing"
    ],
    "answer": "weaving and crafts"
  },
  {
    "question": "'Mo pe o' means",
    "options": [
      "I love you",
      "I see you",
      "I need you",
      "I know you"
    ],
    "answer": "I love you"
  },
  {
    "question": "Yoruba traditional marriage is called",
    "options": [
      "traditional wedding",
      "ceremony",
      "agbala",
      "all of above"
    ],
    "answer": "all of above"
  },
  {
    "question": "Yoruba masks are used for",
    "options": [
      "decoration only",
      "cultural ceremonies",
      "selling",
      "museums"
    ],
    "answer": "cultural ceremonies"
  },
  {
    "question": "Yoruba people are mainly from (Variant 1)",
    "options": [
      "Southern Nigeria",
      "Western Nigeria",
      "Northern Nigeria",
      "Eastern Nigeria"
    ],
    "answer": "Western Nigeria"
  },
  {
    "question": "'Bawo' in Yoruba means (Variant 1)",
    "options": [
      "Goodbye",
      "Hello/How are you",
      "Thank you",
      "Please"
    ],
    "answer": "Hello/How are you"
  },
  {
    "question": "The Yoruba kingdom was called (Variant 1)",
    "options": [
      "Mali",
      "Oyo",
      "Benin",
      "Kano"
    ],
    "answer": "Oyo"
  },
  {
    "question": "Yoruba language has (Variant 1)",
    "options": [
      "3 tones",
      "2 tones",
      "4 tones",
      "5 tones"
    ],
    "answer": "3 tones"
  },
  {
    "question": "Yoruba cultural heritage includes (Variant 1)",
    "options": [
      "only music",
      "art, music, and dance",
      "only dance",
      "only art"
    ],
    "answer": "art, music, and dance"
  },
  {
    "question": "'E pele' in Yoruba means (Variant 1)",
    "options": [
      "Thank you",
      "Sorry/Take it easy",
      "Hello",
      "Goodbye"
    ],
    "answer": "Sorry/Take it easy"
  },
  {
    "question": "Yoruba people are known for (Variant 1)",
    "options": [
      "hunting",
      "weaving and crafts",
      "mining",
      "manufacturing"
    ],
    "answer": "weaving and crafts"
  },
  {
    "question": "'Mo pe o' means (Variant 1)",
    "options": [
      "I love you",
      "I see you",
      "I need you",
      "I know you"
    ],
    "answer": "I love you"
  },
  {
    "question": "Yoruba traditional marriage is called (Variant 1)",
    "options": [
      "traditional wedding",
      "ceremony",
      "agbala",
      "all of above"
    ],
    "answer": "all of above"
  },
  {
    "question": "Yoruba masks are used for (Variant 1)",
    "options": [
      "decoration only",
      "cultural ceremonies",
      "selling",
      "museums"
    ],
    "answer": "cultural ceremonies"
  },
  {
    "question": "Yoruba people are mainly from (Variant 2)",
    "options": [
      "Southern Nigeria",
      "Western Nigeria",
      "Northern Nigeria",
      "Eastern Nigeria"
    ],
    "answer": "Western Nigeria"
  },
  {
    "question": "'Bawo' in Yoruba means (Variant 2)",
    "options": [
      "Goodbye",
      "Hello/How are you",
      "Thank you",
      "Please"
    ],
    "answer": "Hello/How are you"
  },
  {
    "question": "The Yoruba kingdom was called (Variant 2)",
    "options": [
      "Mali",
      "Oyo",
      "Benin",
      "Kano"
    ],
    "answer": "Oyo"
  },
  {
    "question": "Yoruba language has (Variant 2)",
    "options": [
      "3 tones",
      "2 tones",
      "4 tones",
      "5 tones"
    ],
    "answer": "3 tones"
  },
  {
    "question": "Yoruba cultural heritage includes (Variant 2)",
    "options": [
      "only music",
      "art, music, and dance",
      "only dance",
      "only art"
    ],
    "answer": "art, music, and dance"
  },
  {
    "question": "'E pele' in Yoruba means (Variant 2)",
    "options": [
      "Thank you",
      "Sorry/Take it easy",
      "Hello",
      "Goodbye"
    ],
    "answer": "Sorry/Take it easy"
  },
  {
    "question": "Yoruba people are known for (Variant 2)",
    "options": [
      "hunting",
      "weaving and crafts",
      "mining",
      "manufacturing"
    ],
    "answer": "weaving and crafts"
  },
  {
    "question": "'Mo pe o' means (Variant 2)",
    "options": [
      "I love you",
      "I see you",
      "I need you",
      "I know you"
    ],
    "answer": "I love you"
  },
  {
    "question": "Yoruba traditional marriage is called (Variant 2)",
    "options": [
      "traditional wedding",
      "ceremony",
      "agbala",
      "all of above"
    ],
    "answer": "all of above"
  },
  {
    "question": "Yoruba masks are used for (Variant 2)",
    "options": [
      "decoration only",
      "cultural ceremonies",
      "selling",
      "museums"
    ],
    "answer": "cultural ceremonies"
  },
  {
    "question": "Yoruba people are mainly from (Variant 3)",
    "options": [
      "Southern Nigeria",
      "Western Nigeria",
      "Northern Nigeria",
      "Eastern Nigeria"
    ],
    "answer": "Western Nigeria"
  },
  {
    "question": "'Bawo' in Yoruba means (Variant 3)",
    "options": [
      "Goodbye",
      "Hello/How are you",
      "Thank you",
      "Please"
    ],
    "answer": "Hello/How are you"
  },
  {
    "question": "The Yoruba kingdom was called (Variant 3)",
    "options": [
      "Mali",
      "Oyo",
      "Benin",
      "Kano"
    ],
    "answer": "Oyo"
  },
  {
    "question": "Yoruba language has (Variant 3)",
    "options": [
      "3 tones",
      "2 tones",
      "4 tones",
      "5 tones"
    ],
    "answer": "3 tones"
  },
  {
    "question": "Yoruba cultural heritage includes (Variant 3)",
    "options": [
      "only music",
      "art, music, and dance",
      "only dance",
      "only art"
    ],
    "answer": "art, music, and dance"
  },
  {
    "question": "'E pele' in Yoruba means (Variant 3)",
    "options": [
      "Thank you",
      "Sorry/Take it easy",
      "Hello",
      "Goodbye"
    ],
    "answer": "Sorry/Take it easy"
  },
  {
    "question": "Yoruba people are known for (Variant 3)",
    "options": [
      "hunting",
      "weaving and crafts",
      "mining",
      "manufacturing"
    ],
    "answer": "weaving and crafts"
  },
  {
    "question": "'Mo pe o' means (Variant 3)",
    "options": [
      "I love you",
      "I see you",
      "I need you",
      "I know you"
    ],
    "answer": "I love you"
  },
  {
    "question": "Yoruba traditional marriage is called (Variant 3)",
    "options": [
      "traditional wedding",
      "ceremony",
      "agbala",
      "all of above"
    ],
    "answer": "all of above"
  },
  {
    "question": "Yoruba masks are used for (Variant 3)",
    "options": [
      "decoration only",
      "cultural ceremonies",
      "selling",
      "museums"
    ],
    "answer": "cultural ceremonies"
  },
  {
    "question": "Yoruba people are mainly from (Variant 4)",
    "options": [
      "Southern Nigeria",
      "Western Nigeria",
      "Northern Nigeria",
      "Eastern Nigeria"
    ],
    "answer": "Western Nigeria"
  },
  {
    "question": "'Bawo' in Yoruba means (Variant 4)",
    "options": [
      "Goodbye",
      "Hello/How are you",
      "Thank you",
      "Please"
    ],
    "answer": "Hello/How are you"
  },
  {
    "question": "The Yoruba kingdom was called (Variant 4)",
    "options": [
      "Mali",
      "Oyo",
      "Benin",
      "Kano"
    ],
    "answer": "Oyo"
  },
  {
    "question": "Yoruba language has (Variant 4)",
    "options": [
      "3 tones",
      "2 tones",
      "4 tones",
      "5 tones"
    ],
    "answer": "3 tones"
  },
  {
    "question": "Yoruba cultural heritage includes (Variant 4)",
    "options": [
      "only music",
      "art, music, and dance",
      "only dance",
      "only art"
    ],
    "answer": "art, music, and dance"
  },
  {
    "question": "'E pele' in Yoruba means (Variant 4)",
    "options": [
      "Thank you",
      "Sorry/Take it easy",
      "Hello",
      "Goodbye"
    ],
    "answer": "Sorry/Take it easy"
  },
  {
    "question": "Yoruba people are known for (Variant 4)",
    "options": [
      "hunting",
      "weaving and crafts",
      "mining",
      "manufacturing"
    ],
    "answer": "weaving and crafts"
  },
  {
    "question": "'Mo pe o' means (Variant 4)",
    "options": [
      "I love you",
      "I see you",
      "I need you",
      "I know you"
    ],
    "answer": "I love you"
  },
  {
    "question": "Yoruba traditional marriage is called (Variant 4)",
    "options": [
      "traditional wedding",
      "ceremony",
      "agbala",
      "all of above"
    ],
    "answer": "all of above"
  },
  {
    "question": "Yoruba masks are used for (Variant 4)",
    "options": [
      "decoration only",
      "cultural ceremonies",
      "selling",
      "museums"
    ],
    "answer": "cultural ceremonies"
  },
  {
    "question": "Yoruba people are mainly from (Variant 5)",
    "options": [
      "Southern Nigeria",
      "Western Nigeria",
      "Northern Nigeria",
      "Eastern Nigeria"
    ],
    "answer": "Western Nigeria"
  },
  {
    "question": "'Bawo' in Yoruba means (Variant 5)",
    "options": [
      "Goodbye",
      "Hello/How are you",
      "Thank you",
      "Please"
    ],
    "answer": "Hello/How are you"
  },
  {
    "question": "The Yoruba kingdom was called (Variant 5)",
    "options": [
      "Mali",
      "Oyo",
      "Benin",
      "Kano"
    ],
    "answer": "Oyo"
  },
  {
    "question": "Yoruba language has (Variant 5)",
    "options": [
      "3 tones",
      "2 tones",
      "4 tones",
      "5 tones"
    ],
    "answer": "3 tones"
  },
  {
    "question": "Yoruba cultural heritage includes (Variant 5)",
    "options": [
      "only music",
      "art, music, and dance",
      "only dance",
      "only art"
    ],
    "answer": "art, music, and dance"
  },
  {
    "question": "'E pele' in Yoruba means (Variant 5)",
    "options": [
      "Thank you",
      "Sorry/Take it easy",
      "Hello",
      "Goodbye"
    ],
    "answer": "Sorry/Take it easy"
  },
  {
    "question": "Yoruba people are known for (Variant 5)",
    "options": [
      "hunting",
      "weaving and crafts",
      "mining",
      "manufacturing"
    ],
    "answer": "weaving and crafts"
  },
  {
    "question": "'Mo pe o' means (Variant 5)",
    "options": [
      "I love you",
      "I see you",
      "I need you",
      "I know you"
    ],
    "answer": "I love you"
  },
  {
    "question": "Yoruba traditional marriage is called (Variant 5)",
    "options": [
      "traditional wedding",
      "ceremony",
      "agbala",
      "all of above"
    ],
    "answer": "all of above"
  },
  {
    "question": "Yoruba masks are used for (Variant 5)",
    "options": [
      "decoration only",
      "cultural ceremonies",
      "selling",
      "museums"
    ],
    "answer": "cultural ceremonies"
  },
  {
    "question": "Yoruba people are mainly from (Variant 6)",
    "options": [
      "Southern Nigeria",
      "Western Nigeria",
      "Northern Nigeria",
      "Eastern Nigeria"
    ],
    "answer": "Western Nigeria"
  },
  {
    "question": "'Bawo' in Yoruba means (Variant 6)",
    "options": [
      "Goodbye",
      "Hello/How are you",
      "Thank you",
      "Please"
    ],
    "answer": "Hello/How are you"
  },
  {
    "question": "The Yoruba kingdom was called (Variant 6)",
    "options": [
      "Mali",
      "Oyo",
      "Benin",
      "Kano"
    ],
    "answer": "Oyo"
  },
  {
    "question": "Yoruba language has (Variant 6)",
    "options": [
      "3 tones",
      "2 tones",
      "4 tones",
      "5 tones"
    ],
    "answer": "3 tones"
  },
  {
    "question": "Yoruba cultural heritage includes (Variant 6)",
    "options": [
      "only music",
      "art, music, and dance",
      "only dance",
      "only art"
    ],
    "answer": "art, music, and dance"
  },
  {
    "question": "'E pele' in Yoruba means (Variant 6)",
    "options": [
      "Thank you",
      "Sorry/Take it easy",
      "Hello",
      "Goodbye"
    ],
    "answer": "Sorry/Take it easy"
  },
  {
    "question": "Yoruba people are known for (Variant 6)",
    "options": [
      "hunting",
      "weaving and crafts",
      "mining",
      "manufacturing"
    ],
    "answer": "weaving and crafts"
  },
  {
    "question": "'Mo pe o' means (Variant 6)",
    "options": [
      "I love you",
      "I see you",
      "I need you",
      "I know you"
    ],
    "answer": "I love you"
  },
  {
    "question": "Yoruba traditional marriage is called (Variant 6)",
    "options": [
      "traditional wedding",
      "ceremony",
      "agbala",
      "all of above"
    ],
    "answer": "all of above"
  },
  {
    "question": "Yoruba masks are used for (Variant 6)",
    "options": [
      "decoration only",
      "cultural ceremonies",
      "selling",
      "museums"
    ],
    "answer": "cultural ceremonies"
  },
  {
    "question": "Yoruba people are mainly from (Variant 7)",
    "options": [
      "Southern Nigeria",
      "Western Nigeria",
      "Northern Nigeria",
      "Eastern Nigeria"
    ],
    "answer": "Western Nigeria"
  },
  {
    "question": "'Bawo' in Yoruba means (Variant 7)",
    "options": [
      "Goodbye",
      "Hello/How are you",
      "Thank you",
      "Please"
    ],
    "answer": "Hello/How are you"
  },
  {
    "question": "The Yoruba kingdom was called (Variant 7)",
    "options": [
      "Mali",
      "Oyo",
      "Benin",
      "Kano"
    ],
    "answer": "Oyo"
  },
  {
    "question": "Yoruba language has (Variant 7)",
    "options": [
      "3 tones",
      "2 tones",
      "4 tones",
      "5 tones"
    ],
    "answer": "3 tones"
  },
  {
    "question": "Yoruba cultural heritage includes (Variant 7)",
    "options": [
      "only music",
      "art, music, and dance",
      "only dance",
      "only art"
    ],
    "answer": "art, music, and dance"
  },
  {
    "question": "'E pele' in Yoruba means (Variant 7)",
    "options": [
      "Thank you",
      "Sorry/Take it easy",
      "Hello",
      "Goodbye"
    ],
    "answer": "Sorry/Take it easy"
  },
  {
    "question": "Yoruba people are known for (Variant 7)",
    "options": [
      "hunting",
      "weaving and crafts",
      "mining",
      "manufacturing"
    ],
    "answer": "weaving and crafts"
  },
  {
    "question": "'Mo pe o' means (Variant 7)",
    "options": [
      "I love you",
      "I see you",
      "I need you",
      "I know you"
    ],
    "answer": "I love you"
  },
  {
    "question": "Yoruba traditional marriage is called (Variant 7)",
    "options": [
      "traditional wedding",
      "ceremony",
      "agbala",
      "all of above"
    ],
    "answer": "all of above"
  },
  {
    "question": "Yoruba masks are used for (Variant 7)",
    "options": [
      "decoration only",
      "cultural ceremonies",
      "selling",
      "museums"
    ],
    "answer": "cultural ceremonies"
  },
  {
    "question": "Yoruba people are mainly from (Variant 8)",
    "options": [
      "Southern Nigeria",
      "Western Nigeria",
      "Northern Nigeria",
      "Eastern Nigeria"
    ],
    "answer": "Western Nigeria"
  },
  {
    "question": "'Bawo' in Yoruba means (Variant 8)",
    "options": [
      "Goodbye",
      "Hello/How are you",
      "Thank you",
      "Please"
    ],
    "answer": "Hello/How are you"
  },
  {
    "question": "The Yoruba kingdom was called (Variant 8)",
    "options": [
      "Mali",
      "Oyo",
      "Benin",
      "Kano"
    ],
    "answer": "Oyo"
  },
  {
    "question": "Yoruba language has (Variant 8)",
    "options": [
      "3 tones",
      "2 tones",
      "4 tones",
      "5 tones"
    ],
    "answer": "3 tones"
  },
  {
    "question": "Yoruba cultural heritage includes (Variant 8)",
    "options": [
      "only music",
      "art, music, and dance",
      "only dance",
      "only art"
    ],
    "answer": "art, music, and dance"
  },
  {
    "question": "'E pele' in Yoruba means (Variant 8)",
    "options": [
      "Thank you",
      "Sorry/Take it easy",
      "Hello",
      "Goodbye"
    ],
    "answer": "Sorry/Take it easy"
  },
  {
    "question": "Yoruba people are known for (Variant 8)",
    "options": [
      "hunting",
      "weaving and crafts",
      "mining",
      "manufacturing"
    ],
    "answer": "weaving and crafts"
  },
  {
    "question": "'Mo pe o' means (Variant 8)",
    "options": [
      "I love you",
      "I see you",
      "I need you",
      "I know you"
    ],
    "answer": "I love you"
  },
  {
    "question": "Yoruba traditional marriage is called (Variant 8)",
    "options": [
      "traditional wedding",
      "ceremony",
      "agbala",
      "all of above"
    ],
    "answer": "all of above"
  },
  {
    "question": "Yoruba masks are used for (Variant 8)",
    "options": [
      "decoration only",
      "cultural ceremonies",
      "selling",
      "museums"
    ],
    "answer": "cultural ceremonies"
  },
  {
    "question": "Yoruba people are mainly from (Variant 9)",
    "options": [
      "Southern Nigeria",
      "Western Nigeria",
      "Northern Nigeria",
      "Eastern Nigeria"
    ],
    "answer": "Western Nigeria"
  },
  {
    "question": "'Bawo' in Yoruba means (Variant 9)",
    "options": [
      "Goodbye",
      "Hello/How are you",
      "Thank you",
      "Please"
    ],
    "answer": "Hello/How are you"
  },
  {
    "question": "The Yoruba kingdom was called (Variant 9)",
    "options": [
      "Mali",
      "Oyo",
      "Benin",
      "Kano"
    ],
    "answer": "Oyo"
  },
  {
    "question": "Yoruba language has (Variant 9)",
    "options": [
      "3 tones",
      "2 tones",
      "4 tones",
      "5 tones"
    ],
    "answer": "3 tones"
  },
  {
    "question": "Yoruba cultural heritage includes (Variant 9)",
    "options": [
      "only music",
      "art, music, and dance",
      "only dance",
      "only art"
    ],
    "answer": "art, music, and dance"
  },
  {
    "question": "'E pele' in Yoruba means (Variant 9)",
    "options": [
      "Thank you",
      "Sorry/Take it easy",
      "Hello",
      "Goodbye"
    ],
    "answer": "Sorry/Take it easy"
  },
  {
    "question": "Yoruba people are known for (Variant 9)",
    "options": [
      "hunting",
      "weaving and crafts",
      "mining",
      "manufacturing"
    ],
    "answer": "weaving and crafts"
  },
  {
    "question": "'Mo pe o' means (Variant 9)",
    "options": [
      "I love you",
      "I see you",
      "I need you",
      "I know you"
    ],
    "answer": "I love you"
  },
  {
    "question": "Yoruba traditional marriage is called (Variant 9)",
    "options": [
      "traditional wedding",
      "ceremony",
      "agbala",
      "all of above"
    ],
    "answer": "all of above"
  },
  {
    "question": "Yoruba masks are used for (Variant 9)",
    "options": [
      "decoration only",
      "cultural ceremonies",
      "selling",
      "museums"
    ],
    "answer": "cultural ceremonies"
  },
  {
    "question": "Yoruba people are mainly from (Variant 10)",
    "options": [
      "Southern Nigeria",
      "Western Nigeria",
      "Northern Nigeria",
      "Eastern Nigeria"
    ],
    "answer": "Western Nigeria"
  },
  {
    "question": "'Bawo' in Yoruba means (Variant 10)",
    "options": [
      "Goodbye",
      "Hello/How are you",
      "Thank you",
      "Please"
    ],
    "answer": "Hello/How are you"
  },
  {
    "question": "The Yoruba kingdom was called (Variant 10)",
    "options": [
      "Mali",
      "Oyo",
      "Benin",
      "Kano"
    ],
    "answer": "Oyo"
  },
  {
    "question": "Yoruba language has (Variant 10)",
    "options": [
      "3 tones",
      "2 tones",
      "4 tones",
      "5 tones"
    ],
    "answer": "3 tones"
  },
  {
    "question": "Yoruba cultural heritage includes (Variant 10)",
    "options": [
      "only music",
      "art, music, and dance",
      "only dance",
      "only art"
    ],
    "answer": "art, music, and dance"
  },
  {
    "question": "'E pele' in Yoruba means (Variant 10)",
    "options": [
      "Thank you",
      "Sorry/Take it easy",
      "Hello",
      "Goodbye"
    ],
    "answer": "Sorry/Take it easy"
  },
  {
    "question": "Yoruba people are known for (Variant 10)",
    "options": [
      "hunting",
      "weaving and crafts",
      "mining",
      "manufacturing"
    ],
    "answer": "weaving and crafts"
  },
  {
    "question": "'Mo pe o' means (Variant 10)",
    "options": [
      "I love you",
      "I see you",
      "I need you",
      "I know you"
    ],
    "answer": "I love you"
  },
  {
    "question": "Yoruba traditional marriage is called (Variant 10)",
    "options": [
      "traditional wedding",
      "ceremony",
      "agbala",
      "all of above"
    ],
    "answer": "all of above"
  },
  {
    "question": "Yoruba masks are used for (Variant 10)",
    "options": [
      "decoration only",
      "cultural ceremonies",
      "selling",
      "museums"
    ],
    "answer": "cultural ceremonies"
  },
  {
    "question": "Yoruba people are mainly from (Variant 11)",
    "options": [
      "Southern Nigeria",
      "Western Nigeria",
      "Northern Nigeria",
      "Eastern Nigeria"
    ],
    "answer": "Western Nigeria"
  },
  {
    "question": "'Bawo' in Yoruba means (Variant 11)",
    "options": [
      "Goodbye",
      "Hello/How are you",
      "Thank you",
      "Please"
    ],
    "answer": "Hello/How are you"
  },
  {
    "question": "The Yoruba kingdom was called (Variant 11)",
    "options": [
      "Mali",
      "Oyo",
      "Benin",
      "Kano"
    ],
    "answer": "Oyo"
  },
  {
    "question": "Yoruba language has (Variant 11)",
    "options": [
      "3 tones",
      "2 tones",
      "4 tones",
      "5 tones"
    ],
    "answer": "3 tones"
  },
  {
    "question": "Yoruba cultural heritage includes (Variant 11)",
    "options": [
      "only music",
      "art, music, and dance",
      "only dance",
      "only art"
    ],
    "answer": "art, music, and dance"
  },
  {
    "question": "'E pele' in Yoruba means (Variant 11)",
    "options": [
      "Thank you",
      "Sorry/Take it easy",
      "Hello",
      "Goodbye"
    ],
    "answer": "Sorry/Take it easy"
  },
  {
    "question": "Yoruba people are known for (Variant 11)",
    "options": [
      "hunting",
      "weaving and crafts",
      "mining",
      "manufacturing"
    ],
    "answer": "weaving and crafts"
  },
  {
    "question": "'Mo pe o' means (Variant 11)",
    "options": [
      "I love you",
      "I see you",
      "I need you",
      "I know you"
    ],
    "answer": "I love you"
  },
  {
    "question": "Yoruba traditional marriage is called (Variant 11)",
    "options": [
      "traditional wedding",
      "ceremony",
      "agbala",
      "all of above"
    ],
    "answer": "all of above"
  },
  {
    "question": "Yoruba masks are used for (Variant 11)",
    "options": [
      "decoration only",
      "cultural ceremonies",
      "selling",
      "museums"
    ],
    "answer": "cultural ceremonies"
  },
  {
    "question": "Yoruba people are mainly from (Variant 12)",
    "options": [
      "Southern Nigeria",
      "Western Nigeria",
      "Northern Nigeria",
      "Eastern Nigeria"
    ],
    "answer": "Western Nigeria"
  },
  {
    "question": "'Bawo' in Yoruba means (Variant 12)",
    "options": [
      "Goodbye",
      "Hello/How are you",
      "Thank you",
      "Please"
    ],
    "answer": "Hello/How are you"
  },
  {
    "question": "The Yoruba kingdom was called (Variant 12)",
    "options": [
      "Mali",
      "Oyo",
      "Benin",
      "Kano"
    ],
    "answer": "Oyo"
  },
  {
    "question": "Yoruba language has (Variant 12)",
    "options": [
      "3 tones",
      "2 tones",
      "4 tones",
      "5 tones"
    ],
    "answer": "3 tones"
  },
  {
    "question": "Yoruba cultural heritage includes (Variant 12)",
    "options": [
      "only music",
      "art, music, and dance",
      "only dance",
      "only art"
    ],
    "answer": "art, music, and dance"
  },
  {
    "question": "'E pele' in Yoruba means (Variant 12)",
    "options": [
      "Thank you",
      "Sorry/Take it easy",
      "Hello",
      "Goodbye"
    ],
    "answer": "Sorry/Take it easy"
  },
  {
    "question": "Yoruba people are known for (Variant 12)",
    "options": [
      "hunting",
      "weaving and crafts",
      "mining",
      "manufacturing"
    ],
    "answer": "weaving and crafts"
  },
  {
    "question": "'Mo pe o' means (Variant 12)",
    "options": [
      "I love you",
      "I see you",
      "I need you",
      "I know you"
    ],
    "answer": "I love you"
  },
  {
    "question": "Yoruba traditional marriage is called (Variant 12)",
    "options": [
      "traditional wedding",
      "ceremony",
      "agbala",
      "all of above"
    ],
    "answer": "all of above"
  },
  {
    "question": "Yoruba masks are used for (Variant 12)",
    "options": [
      "decoration only",
      "cultural ceremonies",
      "selling",
      "museums"
    ],
    "answer": "cultural ceremonies"
  },
  {
    "question": "Yoruba people are mainly from (Variant 13)",
    "options": [
      "Southern Nigeria",
      "Western Nigeria",
      "Northern Nigeria",
      "Eastern Nigeria"
    ],
    "answer": "Western Nigeria"
  },
  {
    "question": "'Bawo' in Yoruba means (Variant 13)",
    "options": [
      "Goodbye",
      "Hello/How are you",
      "Thank you",
      "Please"
    ],
    "answer": "Hello/How are you"
  },
  {
    "question": "The Yoruba kingdom was called (Variant 13)",
    "options": [
      "Mali",
      "Oyo",
      "Benin",
      "Kano"
    ],
    "answer": "Oyo"
  },
  {
    "question": "Yoruba language has (Variant 13)",
    "options": [
      "3 tones",
      "2 tones",
      "4 tones",
      "5 tones"
    ],
    "answer": "3 tones"
  },
  {
    "question": "Yoruba cultural heritage includes (Variant 13)",
    "options": [
      "only music",
      "art, music, and dance",
      "only dance",
      "only art"
    ],
    "answer": "art, music, and dance"
  },
  {
    "question": "'E pele' in Yoruba means (Variant 13)",
    "options": [
      "Thank you",
      "Sorry/Take it easy",
      "Hello",
      "Goodbye"
    ],
    "answer": "Sorry/Take it easy"
  },
  {
    "question": "Yoruba people are known for (Variant 13)",
    "options": [
      "hunting",
      "weaving and crafts",
      "mining",
      "manufacturing"
    ],
    "answer": "weaving and crafts"
  },
  {
    "question": "'Mo pe o' means (Variant 13)",
    "options": [
      "I love you",
      "I see you",
      "I need you",
      "I know you"
    ],
    "answer": "I love you"
  },
  {
    "question": "Yoruba traditional marriage is called (Variant 13)",
    "options": [
      "traditional wedding",
      "ceremony",
      "agbala",
      "all of above"
    ],
    "answer": "all of above"
  },
  {
    "question": "Yoruba masks are used for (Variant 13)",
    "options": [
      "decoration only",
      "cultural ceremonies",
      "selling",
      "museums"
    ],
    "answer": "cultural ceremonies"
  },
  {
    "question": "Yoruba people are mainly from (Variant 14)",
    "options": [
      "Southern Nigeria",
      "Western Nigeria",
      "Northern Nigeria",
      "Eastern Nigeria"
    ],
    "answer": "Western Nigeria"
  },
  {
    "question": "'Bawo' in Yoruba means (Variant 14)",
    "options": [
      "Goodbye",
      "Hello/How are you",
      "Thank you",
      "Please"
    ],
    "answer": "Hello/How are you"
  },
  {
    "question": "The Yoruba kingdom was called (Variant 14)",
    "options": [
      "Mali",
      "Oyo",
      "Benin",
      "Kano"
    ],
    "answer": "Oyo"
  },
  {
    "question": "Yoruba language has (Variant 14)",
    "options": [
      "3 tones",
      "2 tones",
      "4 tones",
      "5 tones"
    ],
    "answer": "3 tones"
  },
  {
    "question": "Yoruba cultural heritage includes (Variant 14)",
    "options": [
      "only music",
      "art, music, and dance",
      "only dance",
      "only art"
    ],
    "answer": "art, music, and dance"
  },
  {
    "question": "'E pele' in Yoruba means (Variant 14)",
    "options": [
      "Thank you",
      "Sorry/Take it easy",
      "Hello",
      "Goodbye"
    ],
    "answer": "Sorry/Take it easy"
  },
  {
    "question": "Yoruba people are known for (Variant 14)",
    "options": [
      "hunting",
      "weaving and crafts",
      "mining",
      "manufacturing"
    ],
    "answer": "weaving and crafts"
  },
  {
    "question": "'Mo pe o' means (Variant 14)",
    "options": [
      "I love you",
      "I see you",
      "I need you",
      "I know you"
    ],
    "answer": "I love you"
  },
  {
    "question": "Yoruba traditional marriage is called (Variant 14)",
    "options": [
      "traditional wedding",
      "ceremony",
      "agbala",
      "all of above"
    ],
    "answer": "all of above"
  },
  {
    "question": "Yoruba masks are used for (Variant 14)",
    "options": [
      "decoration only",
      "cultural ceremonies",
      "selling",
      "museums"
    ],
    "answer": "cultural ceremonies"
  },
  {
    "question": "Yoruba people are mainly from (Variant 15)",
    "options": [
      "Southern Nigeria",
      "Western Nigeria",
      "Northern Nigeria",
      "Eastern Nigeria"
    ],
    "answer": "Western Nigeria"
  },
  {
    "question": "'Bawo' in Yoruba means (Variant 15)",
    "options": [
      "Goodbye",
      "Hello/How are you",
      "Thank you",
      "Please"
    ],
    "answer": "Hello/How are you"
  },
  {
    "question": "The Yoruba kingdom was called (Variant 15)",
    "options": [
      "Mali",
      "Oyo",
      "Benin",
      "Kano"
    ],
    "answer": "Oyo"
  },
  {
    "question": "Yoruba language has (Variant 15)",
    "options": [
      "3 tones",
      "2 tones",
      "4 tones",
      "5 tones"
    ],
    "answer": "3 tones"
  },
  {
    "question": "Yoruba cultural heritage includes (Variant 15)",
    "options": [
      "only music",
      "art, music, and dance",
      "only dance",
      "only art"
    ],
    "answer": "art, music, and dance"
  },
  {
    "question": "'E pele' in Yoruba means (Variant 15)",
    "options": [
      "Thank you",
      "Sorry/Take it easy",
      "Hello",
      "Goodbye"
    ],
    "answer": "Sorry/Take it easy"
  },
  {
    "question": "Yoruba people are known for (Variant 15)",
    "options": [
      "hunting",
      "weaving and crafts",
      "mining",
      "manufacturing"
    ],
    "answer": "weaving and crafts"
  },
  {
    "question": "'Mo pe o' means (Variant 15)",
    "options": [
      "I love you",
      "I see you",
      "I need you",
      "I know you"
    ],
    "answer": "I love you"
  },
  {
    "question": "Yoruba traditional marriage is called (Variant 15)",
    "options": [
      "traditional wedding",
      "ceremony",
      "agbala",
      "all of above"
    ],
    "answer": "all of above"
  },
  {
    "question": "Yoruba masks are used for (Variant 15)",
    "options": [
      "decoration only",
      "cultural ceremonies",
      "selling",
      "museums"
    ],
    "answer": "cultural ceremonies"
  },
  {
    "question": "Yoruba people are mainly from (Variant 16)",
    "options": [
      "Southern Nigeria",
      "Western Nigeria",
      "Northern Nigeria",
      "Eastern Nigeria"
    ],
    "answer": "Western Nigeria"
  },
  {
    "question": "'Bawo' in Yoruba means (Variant 16)",
    "options": [
      "Goodbye",
      "Hello/How are you",
      "Thank you",
      "Please"
    ],
    "answer": "Hello/How are you"
  },
  {
    "question": "The Yoruba kingdom was called (Variant 16)",
    "options": [
      "Mali",
      "Oyo",
      "Benin",
      "Kano"
    ],
    "answer": "Oyo"
  },
  {
    "question": "Yoruba language has (Variant 16)",
    "options": [
      "3 tones",
      "2 tones",
      "4 tones",
      "5 tones"
    ],
    "answer": "3 tones"
  },
  {
    "question": "Yoruba cultural heritage includes (Variant 16)",
    "options": [
      "only music",
      "art, music, and dance",
      "only dance",
      "only art"
    ],
    "answer": "art, music, and dance"
  },
  {
    "question": "'E pele' in Yoruba means (Variant 16)",
    "options": [
      "Thank you",
      "Sorry/Take it easy",
      "Hello",
      "Goodbye"
    ],
    "answer": "Sorry/Take it easy"
  },
  {
    "question": "Yoruba people are known for (Variant 16)",
    "options": [
      "hunting",
      "weaving and crafts",
      "mining",
      "manufacturing"
    ],
    "answer": "weaving and crafts"
  },
  {
    "question": "'Mo pe o' means (Variant 16)",
    "options": [
      "I love you",
      "I see you",
      "I need you",
      "I know you"
    ],
    "answer": "I love you"
  },
  {
    "question": "Yoruba traditional marriage is called (Variant 16)",
    "options": [
      "traditional wedding",
      "ceremony",
      "agbala",
      "all of above"
    ],
    "answer": "all of above"
  },
  {
    "question": "Yoruba masks are used for (Variant 16)",
    "options": [
      "decoration only",
      "cultural ceremonies",
      "selling",
      "museums"
    ],
    "answer": "cultural ceremonies"
  },
  {
    "question": "Yoruba people are mainly from (Variant 17)",
    "options": [
      "Southern Nigeria",
      "Western Nigeria",
      "Northern Nigeria",
      "Eastern Nigeria"
    ],
    "answer": "Western Nigeria"
  },
  {
    "question": "'Bawo' in Yoruba means (Variant 17)",
    "options": [
      "Goodbye",
      "Hello/How are you",
      "Thank you",
      "Please"
    ],
    "answer": "Hello/How are you"
  },
  {
    "question": "The Yoruba kingdom was called (Variant 17)",
    "options": [
      "Mali",
      "Oyo",
      "Benin",
      "Kano"
    ],
    "answer": "Oyo"
  },
  {
    "question": "Yoruba language has (Variant 17)",
    "options": [
      "3 tones",
      "2 tones",
      "4 tones",
      "5 tones"
    ],
    "answer": "3 tones"
  },
  {
    "question": "Yoruba cultural heritage includes (Variant 17)",
    "options": [
      "only music",
      "art, music, and dance",
      "only dance",
      "only art"
    ],
    "answer": "art, music, and dance"
  },
  {
    "question": "'E pele' in Yoruba means (Variant 17)",
    "options": [
      "Thank you",
      "Sorry/Take it easy",
      "Hello",
      "Goodbye"
    ],
    "answer": "Sorry/Take it easy"
  },
  {
    "question": "Yoruba people are known for (Variant 17)",
    "options": [
      "hunting",
      "weaving and crafts",
      "mining",
      "manufacturing"
    ],
    "answer": "weaving and crafts"
  },
  {
    "question": "'Mo pe o' means (Variant 17)",
    "options": [
      "I love you",
      "I see you",
      "I need you",
      "I know you"
    ],
    "answer": "I love you"
  },
  {
    "question": "Yoruba traditional marriage is called (Variant 17)",
    "options": [
      "traditional wedding",
      "ceremony",
      "agbala",
      "all of above"
    ],
    "answer": "all of above"
  },
  {
    "question": "Yoruba masks are used for (Variant 17)",
    "options": [
      "decoration only",
      "cultural ceremonies",
      "selling",
      "museums"
    ],
    "answer": "cultural ceremonies"
  },
  {
    "question": "Yoruba people are mainly from (Variant 18)",
    "options": [
      "Southern Nigeria",
      "Western Nigeria",
      "Northern Nigeria",
      "Eastern Nigeria"
    ],
    "answer": "Western Nigeria"
  },
  {
    "question": "'Bawo' in Yoruba means (Variant 18)",
    "options": [
      "Goodbye",
      "Hello/How are you",
      "Thank you",
      "Please"
    ],
    "answer": "Hello/How are you"
  },
  {
    "question": "The Yoruba kingdom was called (Variant 18)",
    "options": [
      "Mali",
      "Oyo",
      "Benin",
      "Kano"
    ],
    "answer": "Oyo"
  },
  {
    "question": "Yoruba language has (Variant 18)",
    "options": [
      "3 tones",
      "2 tones",
      "4 tones",
      "5 tones"
    ],
    "answer": "3 tones"
  },
  {
    "question": "Yoruba cultural heritage includes (Variant 18)",
    "options": [
      "only music",
      "art, music, and dance",
      "only dance",
      "only art"
    ],
    "answer": "art, music, and dance"
  },
  {
    "question": "'E pele' in Yoruba means (Variant 18)",
    "options": [
      "Thank you",
      "Sorry/Take it easy",
      "Hello",
      "Goodbye"
    ],
    "answer": "Sorry/Take it easy"
  },
  {
    "question": "Yoruba people are known for (Variant 18)",
    "options": [
      "hunting",
      "weaving and crafts",
      "mining",
      "manufacturing"
    ],
    "answer": "weaving and crafts"
  },
  {
    "question": "'Mo pe o' means (Variant 18)",
    "options": [
      "I love you",
      "I see you",
      "I need you",
      "I know you"
    ],
    "answer": "I love you"
  },
  {
    "question": "Yoruba traditional marriage is called (Variant 18)",
    "options": [
      "traditional wedding",
      "ceremony",
      "agbala",
      "all of above"
    ],
    "answer": "all of above"
  },
  {
    "question": "Yoruba masks are used for (Variant 18)",
    "options": [
      "decoration only",
      "cultural ceremonies",
      "selling",
      "museums"
    ],
    "answer": "cultural ceremonies"
  },
  {
    "question": "Yoruba people are mainly from (Variant 19)",
    "options": [
      "Southern Nigeria",
      "Western Nigeria",
      "Northern Nigeria",
      "Eastern Nigeria"
    ],
    "answer": "Western Nigeria"
  },
  {
    "question": "'Bawo' in Yoruba means (Variant 19)",
    "options": [
      "Goodbye",
      "Hello/How are you",
      "Thank you",
      "Please"
    ],
    "answer": "Hello/How are you"
  },
  {
    "question": "The Yoruba kingdom was called (Variant 19)",
    "options": [
      "Mali",
      "Oyo",
      "Benin",
      "Kano"
    ],
    "answer": "Oyo"
  },
  {
    "question": "Yoruba language has (Variant 19)",
    "options": [
      "3 tones",
      "2 tones",
      "4 tones",
      "5 tones"
    ],
    "answer": "3 tones"
  },
  {
    "question": "Yoruba cultural heritage includes (Variant 19)",
    "options": [
      "only music",
      "art, music, and dance",
      "only dance",
      "only art"
    ],
    "answer": "art, music, and dance"
  },
  {
    "question": "'E pele' in Yoruba means (Variant 19)",
    "options": [
      "Thank you",
      "Sorry/Take it easy",
      "Hello",
      "Goodbye"
    ],
    "answer": "Sorry/Take it easy"
  },
  {
    "question": "Yoruba people are known for (Variant 19)",
    "options": [
      "hunting",
      "weaving and crafts",
      "mining",
      "manufacturing"
    ],
    "answer": "weaving and crafts"
  },
  {
    "question": "'Mo pe o' means (Variant 19)",
    "options": [
      "I love you",
      "I see you",
      "I need you",
      "I know you"
    ],
    "answer": "I love you"
  },
  {
    "question": "Yoruba traditional marriage is called (Variant 19)",
    "options": [
      "traditional wedding",
      "ceremony",
      "agbala",
      "all of above"
    ],
    "answer": "all of above"
  },
  {
    "question": "Yoruba masks are used for (Variant 19)",
    "options": [
      "decoration only",
      "cultural ceremonies",
      "selling",
      "museums"
    ],
    "answer": "cultural ceremonies"
  },
  {
    "question": "Yoruba people are mainly from (Variant 20)",
    "options": [
      "Southern Nigeria",
      "Western Nigeria",
      "Northern Nigeria",
      "Eastern Nigeria"
    ],
    "answer": "Western Nigeria"
  },
  {
    "question": "'Bawo' in Yoruba means (Variant 20)",
    "options": [
      "Goodbye",
      "Hello/How are you",
      "Thank you",
      "Please"
    ],
    "answer": "Hello/How are you"
  },
  {
    "question": "The Yoruba kingdom was called (Variant 20)",
    "options": [
      "Mali",
      "Oyo",
      "Benin",
      "Kano"
    ],
    "answer": "Oyo"
  },
  {
    "question": "Yoruba language has (Variant 20)",
    "options": [
      "3 tones",
      "2 tones",
      "4 tones",
      "5 tones"
    ],
    "answer": "3 tones"
  },
  {
    "question": "Yoruba cultural heritage includes (Variant 20)",
    "options": [
      "only music",
      "art, music, and dance",
      "only dance",
      "only art"
    ],
    "answer": "art, music, and dance"
  },
  {
    "question": "'E pele' in Yoruba means (Variant 20)",
    "options": [
      "Thank you",
      "Sorry/Take it easy",
      "Hello",
      "Goodbye"
    ],
    "answer": "Sorry/Take it easy"
  },
  {
    "question": "Yoruba people are known for (Variant 20)",
    "options": [
      "hunting",
      "weaving and crafts",
      "mining",
      "manufacturing"
    ],
    "answer": "weaving and crafts"
  },
  {
    "question": "'Mo pe o' means (Variant 20)",
    "options": [
      "I love you",
      "I see you",
      "I need you",
      "I know you"
    ],
    "answer": "I love you"
  },
  {
    "question": "Yoruba traditional marriage is called (Variant 20)",
    "options": [
      "traditional wedding",
      "ceremony",
      "agbala",
      "all of above"
    ],
    "answer": "all of above"
  },
  {
    "question": "Yoruba masks are used for (Variant 20)",
    "options": [
      "decoration only",
      "cultural ceremonies",
      "selling",
      "museums"
    ],
    "answer": "cultural ceremonies"
  },
  {
    "question": "Yoruba people are mainly from (Variant 21)",
    "options": [
      "Southern Nigeria",
      "Western Nigeria",
      "Northern Nigeria",
      "Eastern Nigeria"
    ],
    "answer": "Western Nigeria"
  },
  {
    "question": "'Bawo' in Yoruba means (Variant 21)",
    "options": [
      "Goodbye",
      "Hello/How are you",
      "Thank you",
      "Please"
    ],
    "answer": "Hello/How are you"
  },
  {
    "question": "The Yoruba kingdom was called (Variant 21)",
    "options": [
      "Mali",
      "Oyo",
      "Benin",
      "Kano"
    ],
    "answer": "Oyo"
  },
  {
    "question": "Yoruba language has (Variant 21)",
    "options": [
      "3 tones",
      "2 tones",
      "4 tones",
      "5 tones"
    ],
    "answer": "3 tones"
  },
  {
    "question": "Yoruba cultural heritage includes (Variant 21)",
    "options": [
      "only music",
      "art, music, and dance",
      "only dance",
      "only art"
    ],
    "answer": "art, music, and dance"
  },
  {
    "question": "'E pele' in Yoruba means (Variant 21)",
    "options": [
      "Thank you",
      "Sorry/Take it easy",
      "Hello",
      "Goodbye"
    ],
    "answer": "Sorry/Take it easy"
  },
  {
    "question": "Yoruba people are known for (Variant 21)",
    "options": [
      "hunting",
      "weaving and crafts",
      "mining",
      "manufacturing"
    ],
    "answer": "weaving and crafts"
  },
  {
    "question": "'Mo pe o' means (Variant 21)",
    "options": [
      "I love you",
      "I see you",
      "I need you",
      "I know you"
    ],
    "answer": "I love you"
  },
  {
    "question": "Yoruba traditional marriage is called (Variant 21)",
    "options": [
      "traditional wedding",
      "ceremony",
      "agbala",
      "all of above"
    ],
    "answer": "all of above"
  },
  {
    "question": "Yoruba masks are used for (Variant 21)",
    "options": [
      "decoration only",
      "cultural ceremonies",
      "selling",
      "museums"
    ],
    "answer": "cultural ceremonies"
  },
  {
    "question": "Yoruba people are mainly from (Variant 22)",
    "options": [
      "Southern Nigeria",
      "Western Nigeria",
      "Northern Nigeria",
      "Eastern Nigeria"
    ],
    "answer": "Western Nigeria"
  },
  {
    "question": "'Bawo' in Yoruba means (Variant 22)",
    "options": [
      "Goodbye",
      "Hello/How are you",
      "Thank you",
      "Please"
    ],
    "answer": "Hello/How are you"
  },
  {
    "question": "The Yoruba kingdom was called (Variant 22)",
    "options": [
      "Mali",
      "Oyo",
      "Benin",
      "Kano"
    ],
    "answer": "Oyo"
  },
  {
    "question": "Yoruba language has (Variant 22)",
    "options": [
      "3 tones",
      "2 tones",
      "4 tones",
      "5 tones"
    ],
    "answer": "3 tones"
  },
  {
    "question": "Yoruba cultural heritage includes (Variant 22)",
    "options": [
      "only music",
      "art, music, and dance",
      "only dance",
      "only art"
    ],
    "answer": "art, music, and dance"
  },
  {
    "question": "'E pele' in Yoruba means (Variant 22)",
    "options": [
      "Thank you",
      "Sorry/Take it easy",
      "Hello",
      "Goodbye"
    ],
    "answer": "Sorry/Take it easy"
  },
  {
    "question": "Yoruba people are known for (Variant 22)",
    "options": [
      "hunting",
      "weaving and crafts",
      "mining",
      "manufacturing"
    ],
    "answer": "weaving and crafts"
  },
  {
    "question": "'Mo pe o' means (Variant 22)",
    "options": [
      "I love you",
      "I see you",
      "I need you",
      "I know you"
    ],
    "answer": "I love you"
  },
  {
    "question": "Yoruba traditional marriage is called (Variant 22)",
    "options": [
      "traditional wedding",
      "ceremony",
      "agbala",
      "all of above"
    ],
    "answer": "all of above"
  },
  {
    "question": "Yoruba masks are used for (Variant 22)",
    "options": [
      "decoration only",
      "cultural ceremonies",
      "selling",
      "museums"
    ],
    "answer": "cultural ceremonies"
  },
  {
    "question": "Yoruba people are mainly from (Variant 23)",
    "options": [
      "Southern Nigeria",
      "Western Nigeria",
      "Northern Nigeria",
      "Eastern Nigeria"
    ],
    "answer": "Western Nigeria"
  },
  {
    "question": "'Bawo' in Yoruba means (Variant 23)",
    "options": [
      "Goodbye",
      "Hello/How are you",
      "Thank you",
      "Please"
    ],
    "answer": "Hello/How are you"
  },
  {
    "question": "The Yoruba kingdom was called (Variant 23)",
    "options": [
      "Mali",
      "Oyo",
      "Benin",
      "Kano"
    ],
    "answer": "Oyo"
  },
  {
    "question": "Yoruba language has (Variant 23)",
    "options": [
      "3 tones",
      "2 tones",
      "4 tones",
      "5 tones"
    ],
    "answer": "3 tones"
  },
  {
    "question": "Yoruba cultural heritage includes (Variant 23)",
    "options": [
      "only music",
      "art, music, and dance",
      "only dance",
      "only art"
    ],
    "answer": "art, music, and dance"
  },
  {
    "question": "'E pele' in Yoruba means (Variant 23)",
    "options": [
      "Thank you",
      "Sorry/Take it easy",
      "Hello",
      "Goodbye"
    ],
    "answer": "Sorry/Take it easy"
  },
  {
    "question": "Yoruba people are known for (Variant 23)",
    "options": [
      "hunting",
      "weaving and crafts",
      "mining",
      "manufacturing"
    ],
    "answer": "weaving and crafts"
  },
  {
    "question": "'Mo pe o' means (Variant 23)",
    "options": [
      "I love you",
      "I see you",
      "I need you",
      "I know you"
    ],
    "answer": "I love you"
  },
  {
    "question": "Yoruba traditional marriage is called (Variant 23)",
    "options": [
      "traditional wedding",
      "ceremony",
      "agbala",
      "all of above"
    ],
    "answer": "all of above"
  },
  {
    "question": "Yoruba masks are used for (Variant 23)",
    "options": [
      "decoration only",
      "cultural ceremonies",
      "selling",
      "museums"
    ],
    "answer": "cultural ceremonies"
  },
  {
    "question": "Yoruba people are mainly from (Variant 24)",
    "options": [
      "Southern Nigeria",
      "Western Nigeria",
      "Northern Nigeria",
      "Eastern Nigeria"
    ],
    "answer": "Western Nigeria"
  },
  {
    "question": "'Bawo' in Yoruba means (Variant 24)",
    "options": [
      "Goodbye",
      "Hello/How are you",
      "Thank you",
      "Please"
    ],
    "answer": "Hello/How are you"
  },
  {
    "question": "The Yoruba kingdom was called (Variant 24)",
    "options": [
      "Mali",
      "Oyo",
      "Benin",
      "Kano"
    ],
    "answer": "Oyo"
  },
  {
    "question": "Yoruba language has (Variant 24)",
    "options": [
      "3 tones",
      "2 tones",
      "4 tones",
      "5 tones"
    ],
    "answer": "3 tones"
  },
  {
    "question": "Yoruba cultural heritage includes (Variant 24)",
    "options": [
      "only music",
      "art, music, and dance",
      "only dance",
      "only art"
    ],
    "answer": "art, music, and dance"
  },
  {
    "question": "'E pele' in Yoruba means (Variant 24)",
    "options": [
      "Thank you",
      "Sorry/Take it easy",
      "Hello",
      "Goodbye"
    ],
    "answer": "Sorry/Take it easy"
  },
  {
    "question": "Yoruba people are known for (Variant 24)",
    "options": [
      "hunting",
      "weaving and crafts",
      "mining",
      "manufacturing"
    ],
    "answer": "weaving and crafts"
  },
  {
    "question": "'Mo pe o' means (Variant 24)",
    "options": [
      "I love you",
      "I see you",
      "I need you",
      "I know you"
    ],
    "answer": "I love you"
  },
  {
    "question": "Yoruba traditional marriage is called (Variant 24)",
    "options": [
      "traditional wedding",
      "ceremony",
      "agbala",
      "all of above"
    ],
    "answer": "all of above"
  },
  {
    "question": "Yoruba masks are used for (Variant 24)",
    "options": [
      "decoration only",
      "cultural ceremonies",
      "selling",
      "museums"
    ],
    "answer": "cultural ceremonies"
  },
  {
    "question": "Yoruba people are mainly from (Variant 25)",
    "options": [
      "Southern Nigeria",
      "Western Nigeria",
      "Northern Nigeria",
      "Eastern Nigeria"
    ],
    "answer": "Western Nigeria"
  },
  {
    "question": "'Bawo' in Yoruba means (Variant 25)",
    "options": [
      "Goodbye",
      "Hello/How are you",
      "Thank you",
      "Please"
    ],
    "answer": "Hello/How are you"
  },
  {
    "question": "The Yoruba kingdom was called (Variant 25)",
    "options": [
      "Mali",
      "Oyo",
      "Benin",
      "Kano"
    ],
    "answer": "Oyo"
  },
  {
    "question": "Yoruba language has (Variant 25)",
    "options": [
      "3 tones",
      "2 tones",
      "4 tones",
      "5 tones"
    ],
    "answer": "3 tones"
  },
  {
    "question": "Yoruba cultural heritage includes (Variant 25)",
    "options": [
      "only music",
      "art, music, and dance",
      "only dance",
      "only art"
    ],
    "answer": "art, music, and dance"
  },
  {
    "question": "'E pele' in Yoruba means (Variant 25)",
    "options": [
      "Thank you",
      "Sorry/Take it easy",
      "Hello",
      "Goodbye"
    ],
    "answer": "Sorry/Take it easy"
  },
  {
    "question": "Yoruba people are known for (Variant 25)",
    "options": [
      "hunting",
      "weaving and crafts",
      "mining",
      "manufacturing"
    ],
    "answer": "weaving and crafts"
  },
  {
    "question": "'Mo pe o' means (Variant 25)",
    "options": [
      "I love you",
      "I see you",
      "I need you",
      "I know you"
    ],
    "answer": "I love you"
  },
  {
    "question": "Yoruba traditional marriage is called (Variant 25)",
    "options": [
      "traditional wedding",
      "ceremony",
      "agbala",
      "all of above"
    ],
    "answer": "all of above"
  },
  {
    "question": "Yoruba masks are used for (Variant 25)",
    "options": [
      "decoration only",
      "cultural ceremonies",
      "selling",
      "museums"
    ],
    "answer": "cultural ceremonies"
  },
  {
    "question": "Yoruba people are mainly from (Variant 26)",
    "options": [
      "Southern Nigeria",
      "Western Nigeria",
      "Northern Nigeria",
      "Eastern Nigeria"
    ],
    "answer": "Western Nigeria"
  },
  {
    "question": "'Bawo' in Yoruba means (Variant 26)",
    "options": [
      "Goodbye",
      "Hello/How are you",
      "Thank you",
      "Please"
    ],
    "answer": "Hello/How are you"
  },
  {
    "question": "The Yoruba kingdom was called (Variant 26)",
    "options": [
      "Mali",
      "Oyo",
      "Benin",
      "Kano"
    ],
    "answer": "Oyo"
  },
  {
    "question": "Yoruba language has (Variant 26)",
    "options": [
      "3 tones",
      "2 tones",
      "4 tones",
      "5 tones"
    ],
    "answer": "3 tones"
  },
  {
    "question": "Yoruba cultural heritage includes (Variant 26)",
    "options": [
      "only music",
      "art, music, and dance",
      "only dance",
      "only art"
    ],
    "answer": "art, music, and dance"
  },
  {
    "question": "'E pele' in Yoruba means (Variant 26)",
    "options": [
      "Thank you",
      "Sorry/Take it easy",
      "Hello",
      "Goodbye"
    ],
    "answer": "Sorry/Take it easy"
  },
  {
    "question": "Yoruba people are known for (Variant 26)",
    "options": [
      "hunting",
      "weaving and crafts",
      "mining",
      "manufacturing"
    ],
    "answer": "weaving and crafts"
  },
  {
    "question": "'Mo pe o' means (Variant 26)",
    "options": [
      "I love you",
      "I see you",
      "I need you",
      "I know you"
    ],
    "answer": "I love you"
  },
  {
    "question": "Yoruba traditional marriage is called (Variant 26)",
    "options": [
      "traditional wedding",
      "ceremony",
      "agbala",
      "all of above"
    ],
    "answer": "all of above"
  },
  {
    "question": "Yoruba masks are used for (Variant 26)",
    "options": [
      "decoration only",
      "cultural ceremonies",
      "selling",
      "museums"
    ],
    "answer": "cultural ceremonies"
  },
  {
    "question": "Yoruba people are mainly from (Variant 27)",
    "options": [
      "Southern Nigeria",
      "Western Nigeria",
      "Northern Nigeria",
      "Eastern Nigeria"
    ],
    "answer": "Western Nigeria"
  },
  {
    "question": "'Bawo' in Yoruba means (Variant 27)",
    "options": [
      "Goodbye",
      "Hello/How are you",
      "Thank you",
      "Please"
    ],
    "answer": "Hello/How are you"
  },
  {
    "question": "The Yoruba kingdom was called (Variant 27)",
    "options": [
      "Mali",
      "Oyo",
      "Benin",
      "Kano"
    ],
    "answer": "Oyo"
  },
  {
    "question": "Yoruba language has (Variant 27)",
    "options": [
      "3 tones",
      "2 tones",
      "4 tones",
      "5 tones"
    ],
    "answer": "3 tones"
  },
  {
    "question": "Yoruba cultural heritage includes (Variant 27)",
    "options": [
      "only music",
      "art, music, and dance",
      "only dance",
      "only art"
    ],
    "answer": "art, music, and dance"
  },
  {
    "question": "'E pele' in Yoruba means (Variant 27)",
    "options": [
      "Thank you",
      "Sorry/Take it easy",
      "Hello",
      "Goodbye"
    ],
    "answer": "Sorry/Take it easy"
  },
  {
    "question": "Yoruba people are known for (Variant 27)",
    "options": [
      "hunting",
      "weaving and crafts",
      "mining",
      "manufacturing"
    ],
    "answer": "weaving and crafts"
  },
  {
    "question": "'Mo pe o' means (Variant 27)",
    "options": [
      "I love you",
      "I see you",
      "I need you",
      "I know you"
    ],
    "answer": "I love you"
  },
  {
    "question": "Yoruba traditional marriage is called (Variant 27)",
    "options": [
      "traditional wedding",
      "ceremony",
      "agbala",
      "all of above"
    ],
    "answer": "all of above"
  },
  {
    "question": "Yoruba masks are used for (Variant 27)",
    "options": [
      "decoration only",
      "cultural ceremonies",
      "selling",
      "museums"
    ],
    "answer": "cultural ceremonies"
  },
  {
    "question": "Yoruba people are mainly from (Variant 28)",
    "options": [
      "Southern Nigeria",
      "Western Nigeria",
      "Northern Nigeria",
      "Eastern Nigeria"
    ],
    "answer": "Western Nigeria"
  },
  {
    "question": "'Bawo' in Yoruba means (Variant 28)",
    "options": [
      "Goodbye",
      "Hello/How are you",
      "Thank you",
      "Please"
    ],
    "answer": "Hello/How are you"
  },
  {
    "question": "The Yoruba kingdom was called (Variant 28)",
    "options": [
      "Mali",
      "Oyo",
      "Benin",
      "Kano"
    ],
    "answer": "Oyo"
  },
  {
    "question": "Yoruba language has (Variant 28)",
    "options": [
      "3 tones",
      "2 tones",
      "4 tones",
      "5 tones"
    ],
    "answer": "3 tones"
  },
  {
    "question": "Yoruba cultural heritage includes (Variant 28)",
    "options": [
      "only music",
      "art, music, and dance",
      "only dance",
      "only art"
    ],
    "answer": "art, music, and dance"
  },
  {
    "question": "'E pele' in Yoruba means (Variant 28)",
    "options": [
      "Thank you",
      "Sorry/Take it easy",
      "Hello",
      "Goodbye"
    ],
    "answer": "Sorry/Take it easy"
  },
  {
    "question": "Yoruba people are known for (Variant 28)",
    "options": [
      "hunting",
      "weaving and crafts",
      "mining",
      "manufacturing"
    ],
    "answer": "weaving and crafts"
  },
  {
    "question": "'Mo pe o' means (Variant 28)",
    "options": [
      "I love you",
      "I see you",
      "I need you",
      "I know you"
    ],
    "answer": "I love you"
  },
  {
    "question": "Yoruba traditional marriage is called (Variant 28)",
    "options": [
      "traditional wedding",
      "ceremony",
      "agbala",
      "all of above"
    ],
    "answer": "all of above"
  },
  {
    "question": "Yoruba masks are used for (Variant 28)",
    "options": [
      "decoration only",
      "cultural ceremonies",
      "selling",
      "museums"
    ],
    "answer": "cultural ceremonies"
  },
  {
    "question": "Yoruba people are mainly from (Variant 29)",
    "options": [
      "Southern Nigeria",
      "Western Nigeria",
      "Northern Nigeria",
      "Eastern Nigeria"
    ],
    "answer": "Western Nigeria"
  },
  {
    "question": "'Bawo' in Yoruba means (Variant 29)",
    "options": [
      "Goodbye",
      "Hello/How are you",
      "Thank you",
      "Please"
    ],
    "answer": "Hello/How are you"
  },
  {
    "question": "The Yoruba kingdom was called (Variant 29)",
    "options": [
      "Mali",
      "Oyo",
      "Benin",
      "Kano"
    ],
    "answer": "Oyo"
  },
  {
    "question": "Yoruba language has (Variant 29)",
    "options": [
      "3 tones",
      "2 tones",
      "4 tones",
      "5 tones"
    ],
    "answer": "3 tones"
  },
  {
    "question": "Yoruba cultural heritage includes (Variant 29)",
    "options": [
      "only music",
      "art, music, and dance",
      "only dance",
      "only art"
    ],
    "answer": "art, music, and dance"
  },
  {
    "question": "'E pele' in Yoruba means (Variant 29)",
    "options": [
      "Thank you",
      "Sorry/Take it easy",
      "Hello",
      "Goodbye"
    ],
    "answer": "Sorry/Take it easy"
  },
  {
    "question": "Yoruba people are known for (Variant 29)",
    "options": [
      "hunting",
      "weaving and crafts",
      "mining",
      "manufacturing"
    ],
    "answer": "weaving and crafts"
  },
  {
    "question": "'Mo pe o' means (Variant 29)",
    "options": [
      "I love you",
      "I see you",
      "I need you",
      "I know you"
    ],
    "answer": "I love you"
  },
  {
    "question": "Yoruba traditional marriage is called (Variant 29)",
    "options": [
      "traditional wedding",
      "ceremony",
      "agbala",
      "all of above"
    ],
    "answer": "all of above"
  },
  {
    "question": "Yoruba masks are used for (Variant 29)",
    "options": [
      "decoration only",
      "cultural ceremonies",
      "selling",
      "museums"
    ],
    "answer": "cultural ceremonies"
  }
]